MANIFEST.in
setup.py
bin/create_bootstrap_project
django_bootstrap3view_app/__init__.py
django_bootstrap3view_app/models.py
django_bootstrap3view_app/bootstrap/css/bootstrap-theme.css
django_bootstrap3view_app/bootstrap/css/bootstrap-theme.css.map
django_bootstrap3view_app/bootstrap/css/bootstrap-theme.min.css
django_bootstrap3view_app/bootstrap/css/bootstrap.css
django_bootstrap3view_app/bootstrap/css/bootstrap.css.map
django_bootstrap3view_app/bootstrap/css/bootstrap.min.css
django_bootstrap3view_app/bootstrap/css/carousel.css
django_bootstrap3view_app/bootstrap/fonts/glyphicons-halflings-regular.eot
django_bootstrap3view_app/bootstrap/fonts/glyphicons-halflings-regular.svg
django_bootstrap3view_app/bootstrap/fonts/glyphicons-halflings-regular.ttf
django_bootstrap3view_app/bootstrap/fonts/glyphicons-halflings-regular.woff
django_bootstrap3view_app/bootstrap/js/bootstrap.js
django_bootstrap3view_app/bootstrap/js/bootstrap.min.js
django_bootstrap3view_app/bootstrap/js/docs.min.js
django_bootstrap3view_app/management/__init__.py
django_bootstrap3view_app/management/commands/__init__.py
django_bootstrap3view_app/management/commands/compile_css_to_less.py
django_bootstrap3view_app/management/commands/create_bootstrap_project.py
django_bootstrap3view_app/management/commands/lib/__init__.py
django_bootstrap3view_app/management/commands/lib/builder.py
django_bootstrap3view_app/management/commands/lib/templates.py
django_bootstrap3view_app/management/commands/media/favicon.ico
django_bootstrap3view_app/management/commands/templates/index.html
django_bootstrap3view_app/management/commands/templates/index.tm
django_bootstrap3view_app/management/commands/templates/settings.tm
django_bootstrap3view_app/management/commands/templates/urls.tm
django_bootstrap3view_app/services/__init__.py
django_bootstrap3view_app/services/base.py
django_bootstrap3view_app/test/__init__.py
django_bootstrap3view_app/test/test_command.py
django_bootstrap3view_app/utils/__init__.py
django_classview_bootstrap3.egg-info/PKG-INFO
django_classview_bootstrap3.egg-info/SOURCES.txt
django_classview_bootstrap3.egg-info/dependency_links.txt
django_classview_bootstrap3.egg-info/requires.txt
django_classview_bootstrap3.egg-info/top_level.txt