Metadata-Version: 1.1
Name: django-classview-bootstrap3
Version: 0.0.7-r5
Summary: Django-Bootstrap 3 generic template with class views
Home-page: http://bossiernesto.github.io/django-bootstrap3-classview/
Author: Ernesto Bossi
Author-email: bossi.ernestog@gmail.com
License: BSD-3
Platform: UNKNOWN
Classifier: Development Status :: 3 - Alpha
Classifier: Framework :: Django
Classifier: Operating System :: OS Independent
Classifier: Topic :: Software Development
Classifier: Programming Language :: Python :: 2.7
